dsidelib/__init__.py
dsidelib/core.py
dsidelib/disco.py
dsidelib/telega.py
dsidelib-1.2.0.dist-info/METADATA
dsidelib-1.2.0.dist-info/WHEEL
dsidelib-1.2.0.dist-info/top_level.txt
dsidelib-1.2.0.dist-info/RECORD
