Metadata-Version: 2.4
Name: dsidelib
Version: 1.2.0
Summary: Simple example library with run function
Author: fuqasha
Requires-Python: >=3.6
Dynamic: author
Dynamic: requires-python
Dynamic: summary
